simple_entity/__init__.py
simple_entity-0.1.1.dist-info/WHEEL
simple_entity-0.1.1.dist-info/METADATA
simple_entity-0.1.1.dist-info/RECORD
