Metadata-Version: 2.1
Name: simple-entity
Version: 0.1.1
Summary: Simeple Entity Type for DDD development.
Home-page: https://github.com/duyixian1234/simple-entity
License: MIT
Author: duyixian
Author-email: duyixian1234@qq.com
Requires-Python: >=3.8,<4.0
Classifier: License :: OSI Approved :: MIT License
Classifier: Programming Language :: Python :: 3
Classifier: Programming Language :: Python :: 3.8
Classifier: Programming Language :: Python :: 3.9
Requires-Dist: python-dateutil (>=2.8.1,<3.0.0)
Project-URL: Repository, https://github.com/duyixian1234/simple-entity
